std_distributions/Binomialdistribution.py
std_distributions/Gaussiandistribution.py
std_distributions/Generaldistribution.py
std_distributions/__init__.py
std_distributions-1.1.dist-info/METADATA
std_distributions-1.1.dist-info/WHEEL
std_distributions-1.1.dist-info/top_level.txt
std_distributions-1.1.dist-info/RECORD
