Metadata-Version: 2.1
Name: std-distributions
Version: 1.1
Summary: Gaussian and Binomial distributions
Home-page: UNKNOWN
Author: Mutahar Majid
Author-email: mutaharmajid243@gmail.com
License: MIT
Platform: UNKNOWN
